<?xml version="1.0" encoding="UTF-8"?>
<typeSystemDescription xmlns="http://uima.apache.org/resourceSpecifier">
  <name>org.apache.uima.ruta.engine.BasicTypeSystem</name>
  <description/>
  <version>1.0</version>
  <vendor/>
  <imports>
    <import name="org.apache.uima.ruta.engine.InternalTypeSystem"/>
  </imports>
  <types>
    <typeDescription>
      <name>org.apache.uima.ruta.type.ALL</name>
      <description/>
      <supertypeName>org.apache.uima.ruta.type.TokenSeed</supertypeName>
    </typeDescription>
    <typeDescription>
      <name>org.apache.uima.ruta.type.ANY</name>
      <description/>
      <supertypeName>org.apache.uima.ruta.type.ALL</supertypeName>
    </typeDescription>
    <typeDescription>
      <name>org.apache.uima.ruta.type.MARKUP</name>
      <description/>
      <supertypeName>org.apache.uima.ruta.type.ALL</supertypeName>
    </typeDescription>
    <typeDescription>
      <name>org.apache.uima.ruta.type.CW</name>
      <description/>
      <supertypeName>org.apache.uima.ruta.type.W</supertypeName>
    </typeDescription>
    <typeDescription>
      <name>org.apache.uima.ruta.type.W</name>
      <description/>
      <supertypeName>org.apache.uima.ruta.type.ANY</supertypeName>
    </typeDescription>
    <typeDescription>
      <name>org.apache.uima.ruta.type.SW</name>
      <description/>
      <supertypeName>org.apache.uima.ruta.type.W</supertypeName>
    </typeDescription>
    <typeDescription>
      <name>org.apache.uima.ruta.type.PM</name>
      <description/>
      <supertypeName>org.apache.uima.ruta.type.ANY</supertypeName>
    </typeDescription>
    <typeDescription>
      <name>org.apache.uima.ruta.type.CAP</name>
      <description/>
      <supertypeName>org.apache.uima.ruta.type.W</supertypeName>
    </typeDescription>
    <typeDescription>
      <name>org.apache.uima.ruta.type.COLON</name>
      <description/>
      <supertypeName>org.apache.uima.ruta.type.PM</supertypeName>
    </typeDescription>
    <typeDescription>
      <name>org.apache.uima.ruta.type.PERIOD</name>
      <description/>
      <supertypeName>org.apache.uima.ruta.type.SENTENCEEND</supertypeName>
    </typeDescription>
    <typeDescription>
      <name>org.apache.uima.ruta.type.SENTENCEEND</name>
      <description/>
      <supertypeName>org.apache.uima.ruta.type.PM</supertypeName>
    </typeDescription>
    <typeDescription>
      <name>org.apache.uima.ruta.type.QUESTION</name>
      <description/>
      <supertypeName>org.apache.uima.ruta.type.SENTENCEEND</supertypeName>
    </typeDescription>
    <typeDescription>
      <name>org.apache.uima.ruta.type.COMMA</name>
      <description/>
      <supertypeName>org.apache.uima.ruta.type.PM</supertypeName>
    </typeDescription>
    <typeDescription>
      <name>org.apache.uima.ruta.type.EXCLAMATION</name>
      <description/>
      <supertypeName>org.apache.uima.ruta.type.SENTENCEEND</supertypeName>
    </typeDescription>
    <typeDescription>
      <name>org.apache.uima.ruta.type.SEMICOLON</name>
      <description/>
      <supertypeName>org.apache.uima.ruta.type.PM</supertypeName>
    </typeDescription>
    <typeDescription>
      <name>org.apache.uima.ruta.type.WS</name>
      <description/>
      <supertypeName>org.apache.uima.ruta.type.ANY</supertypeName>
    </typeDescription>
    <typeDescription>
      <name>org.apache.uima.ruta.type.NUM</name>
      <description/>
      <supertypeName>org.apache.uima.ruta.type.ANY</supertypeName>
    </typeDescription>
    <typeDescription>
      <name>org.apache.uima.ruta.type.SPECIAL</name>
      <description/>
      <supertypeName>org.apache.uima.ruta.type.ANY</supertypeName>
    </typeDescription>
    <typeDescription>
      <name>org.apache.uima.ruta.type.NBSP</name>
      <description/>
      <supertypeName>org.apache.uima.ruta.type.SPACE</supertypeName>
    </typeDescription>
    <typeDescription>
      <name>org.apache.uima.ruta.type.AMP</name>
      <description/>
      <supertypeName>org.apache.uima.ruta.type.ANY</supertypeName>
    </typeDescription>
    <typeDescription>
      <name>org.apache.uima.ruta.type.SPACE</name>
      <description/>
      <supertypeName>org.apache.uima.ruta.type.WS</supertypeName>
    </typeDescription>
    <typeDescription>
      <name>org.apache.uima.ruta.type.BREAK</name>
      <description/>
      <supertypeName>org.apache.uima.ruta.type.WS</supertypeName>
    </typeDescription>
    <typeDescription>
      <name>org.apache.uima.ruta.type.Document</name>
      <description/>
      <supertypeName>uima.tcas.Annotation</supertypeName>
    </typeDescription>
    <typeDescription>
      <name>org.apache.uima.ruta.type.TokenSeed</name>
      <description/>
      <supertypeName>uima.tcas.Annotation</supertypeName>
    </typeDescription>
  </types>
</typeSystemDescription>
