<?xml version="1.0" encoding="UTF-8"?>
<typeSystemDescription xmlns="http://uima.apache.org/resourceSpecifier">
    <name>uima.ruta.annotators.SingleLineCommentTypeSystem</name>
    <imports>
        <import name="org.apache.uima.ruta.engine.BasicTypeSystem"/>
        <import name="uima.ruta.annotators.JavaTypeSystem"/>
    </imports>
    <types>
        <typeDescription>
            <name>uima.ruta.annotators.SingleLineComment.InitComment</name>
            <description>Type defined in SingleLineComment</description>
            <supertypeName>uima.tcas.Annotation</supertypeName>
        </typeDescription>
    </types>
</typeSystemDescription>
